{
	"$schema": "http://schema.management.azure.com/schemas/2015-01-01/deploymentTemplate.json#",
	"contentVersion": "1.0.0.0",
	"parameters": {
		"factoryName": {
			"type": "string",
			"metadata": "Data Factory name",
			"defaultValue": "group3-df"
		},
		"LS_Databricks_Silver_accessToken": {
			"type": "secureString",
			"metadata": "Secure string for 'accessToken' of 'LS_Databricks_Silver'"
		},
		"LS_AzureFileShare_SAC_connectionString": {
			"type": "secureString",
			"metadata": "Secure string for 'connectionString' of 'LS_AzureFileShare_SAC'",
			"defaultValue": "DefaultEndpointsProtocol=https;AccountName=adlsbellevuegrp3;EndpointSuffix=core.windows.net;"
		},
		"LS_AKV_properties_typeProperties_baseUrl": {
			"type": "string",
			"defaultValue": "https://DataCycleGroup3Keys.vault.azure.net/"
		},
		"AzureDatabricks_properties_typeProperties_existingClusterId": {
			"type": "string",
			"defaultValue": "0223-115927-nvtos4a4"
		},
		"LS_ADLS_Bronze_properties_typeProperties_url": {
			"type": "string",
			"defaultValue": "https://adlsbellevuegrp3.dfs.core.windows.net/"
		},
		"LS_BellevueBooking_LocalServer_properties_typeProperties_host": {
			"type": "string",
			"defaultValue": "\\\\10.130.25.152\\BellevueBooking"
		},
		"LS_BellevueBooking_LocalServer_properties_typeProperties_userId": {
			"type": "string",
			"defaultValue": "Student"
		},
		"LS_BellevueConso_LocalServer_properties_typeProperties_host": {
			"type": "string",
			"defaultValue": "\\\\10.130.25.152\\BellevueConso"
		},
		"LS_BellevueConso_LocalServer_properties_typeProperties_userId": {
			"type": "string",
			"defaultValue": "Student"
		},
		"LS_DevDB_Gold_properties_typeProperties_server": {
			"type": "string",
			"defaultValue": "sqlserver-bellevue-grp3.database.windows.net"
		},
		"LS_DevDB_Gold_properties_typeProperties_database": {
			"type": "string",
			"defaultValue": "DevDB"
		},
		"LS_DevDB_Gold_properties_typeProperties_userName": {
			"type": "string",
			"defaultValue": "dylan.sanderso"
		},
		"LS_SFTP_LocalServer_properties_typeProperties_host": {
			"type": "string",
			"defaultValue": "10.130.25.152"
		},
		"LS_SFTP_LocalServer_properties_typeProperties_userName": {
			"type": "string",
			"defaultValue": "Student"
		},
		"LS_Solarlogs_LocalServer_properties_typeProperties_host": {
			"type": "string",
			"defaultValue": "\\\\10.130.25.152\\Solarlogs"
		},
		"LS_Solarlogs_LocalServer_properties_typeProperties_userId": {
			"type": "string",
			"defaultValue": "Student"
		}
	},
	"variables": {
		"factoryId": "[concat('Microsoft.DataFactory/factories/', parameters('factoryName'))]"
	},
	"resources": [
		{
			"name": "[concat(parameters('factoryName'), '/LS_AKV')]",
			"type": "Microsoft.DataFactory/factories/linkedServices",
			"apiVersion": "2018-06-01",
			"properties": {
				"annotations": [],
				"type": "AzureKeyVault",
				"typeProperties": {
					"baseUrl": "[parameters('LS_AKV_properties_typeProperties_baseUrl')]"
				}
			},
			"dependsOn": []
		},
		{
			"name": "[concat(parameters('factoryName'), '/LS_Databricks_Silver')]",
			"type": "Microsoft.DataFactory/factories/linkedServices",
			"apiVersion": "2018-06-01",
			"properties": {
				"annotations": [],
				"type": "AzureDatabricksDeltaLake",
				"typeProperties": {
					"domain": "https://adb-7405619109510762.2.azuredatabricks.net",
					"clusterId": "0223-115927-nvtos4a4",
					"accessToken": {
						"type": "SecureString",
						"value": "[parameters('LS_Databricks_Silver_accessToken')]"
					}
				}
			},
			"dependsOn": []
		},
		{
			"name": "[concat(parameters('factoryName'), '/Group3-VM-Runtime')]",
			"type": "Microsoft.DataFactory/factories/integrationRuntimes",
			"apiVersion": "2018-06-01",
			"properties": {
				"type": "SelfHosted",
				"typeProperties": {}
			},
			"dependsOn": []
		},
		{
			"name": "[concat(parameters('factoryName'), '/gh-datacycle-oidc')]",
			"type": "Microsoft.DataFactory/factories/credentials",
			"apiVersion": "2018-06-01",
			"properties": {
				"type": "ManagedIdentity",
				"typeProperties": {
					"resourceId": "/subscriptions/852f0176-1826-4957-a7fc-b1cd7e7aac73/resourceGroups/datafactory-rg505/providers/Microsoft.ManagedIdentity/userAssignedIdentities/gh-datacycle-oidc"
				}
			},
			"dependsOn": []
		},
		{
			"name": "[concat(parameters('factoryName'), '/Run_Knime')]",
			"type": "Microsoft.DataFactory/factories/pipelines",
			"apiVersion": "2018-06-01",
			"properties": {
				"activities": [
					{
						"name": "Call_If_Monday",
						"type": "IfCondition",
						"dependsOn": [
							{
								"activity": "Data_Preparation",
								"dependencyConditions": [
									"Succeeded"
								]
							}
						],
						"userProperties": [],
						"typeProperties": {
							"expression": {
								"value": "@equals(dayOfWeek(pipeline().TriggerTime), 1)",
								"type": "Expression"
							},
							"ifTrueActivities": [
								{
									"name": "Call_Model_Selection",
									"type": "WebActivity",
									"dependsOn": [],
									"policy": {
										"timeout": "0.12:00:00",
										"retry": 0,
										"retryIntervalInSeconds": 30,
										"secureOutput": false,
										"secureInput": false
									},
									"userProperties": [],
									"typeProperties": {
										"method": "POST",
										"headers": {
											"Content-Type": "application/json"
										},
										"url": "https://api.edu-hub.knime.com/deployments/rest:509f9c76-1fd3-444d-80a6-4df7848b1621/execution",
										"body": "{}",
										"authentication": {
											"type": "Basic",
											"username": "N8XZA3zjIJVLk-P2XxLKBkLv1_aT-bX302wwgIGOmrY",
											"password": {
												"type": "AzureKeyVaultSecret",
												"store": {
													"referenceName": "LS_AKV",
													"type": "LinkedServiceReference"
												},
												"secretName": "knimeappsecret"
											}
										}
									}
								}
							]
						}
					},
					{
						"name": "Cons",
						"type": "WebActivity",
						"dependsOn": [
							{
								"activity": "Call_If_Monday",
								"dependencyConditions": [
									"Succeeded"
								]
							}
						],
						"policy": {
							"timeout": "0.12:00:00",
							"retry": 0,
							"retryIntervalInSeconds": 30,
							"secureOutput": false,
							"secureInput": false
						},
						"userProperties": [],
						"typeProperties": {
							"method": "POST",
							"headers": {
								"Content-Type": "application/json"
							},
							"url": "https://api.edu-hub.knime.com/deployments/rest:348633fa-f10f-4a27-99de-11e1707190cb/execution",
							"body": "{}",
							"authentication": {
								"type": "Basic",
								"username": "N8XZA3zjIJVLk-P2XxLKBkLv1_aT-bX302wwgIGOmrY",
								"password": {
									"type": "AzureKeyVaultSecret",
									"store": {
										"referenceName": "LS_AKV",
										"type": "LinkedServiceReference"
									},
									"secretName": "knimeappsecret"
								}
							}
						}
					},
					{
						"name": "Solar",
						"type": "WebActivity",
						"dependsOn": [
							{
								"activity": "Call_If_Monday",
								"dependencyConditions": [
									"Succeeded"
								]
							}
						],
						"policy": {
							"timeout": "0.12:00:00",
							"retry": 0,
							"retryIntervalInSeconds": 30,
							"secureOutput": false,
							"secureInput": false
						},
						"userProperties": [],
						"typeProperties": {
							"method": "POST",
							"headers": {
								"Content-Type": "application/json"
							},
							"url": "https://api.edu-hub.knime.com/deployments/rest:eb96aa91-239b-4cf2-8c7e-a8a40516d4f3/execution",
							"body": "{}",
							"authentication": {
								"type": "Basic",
								"username": "N8XZA3zjIJVLk-P2XxLKBkLv1_aT-bX302wwgIGOmrY",
								"password": {
									"type": "AzureKeyVaultSecret",
									"store": {
										"referenceName": "LS_AKV",
										"type": "LinkedServiceReference"
									},
									"secretName": "knimeappsecret"
								}
							}
						}
					},
					{
						"name": "Data_Preparation",
						"type": "WebActivity",
						"dependsOn": [],
						"policy": {
							"timeout": "0.12:00:00",
							"retry": 0,
							"retryIntervalInSeconds": 30,
							"secureOutput": false,
							"secureInput": false
						},
						"userProperties": [],
						"typeProperties": {
							"method": "POST",
							"headers": {
								"Content-Type": "application/json"
							},
							"url": "https://api.edu-hub.knime.com/deployments/rest:e481f0fd-89ba-409a-aaa2-d8a648956949/execution",
							"body": "{}",
							"authentication": {
								"type": "Basic",
								"username": "N8XZA3zjIJVLk-P2XxLKBkLv1_aT-bX302wwgIGOmrY",
								"password": {
									"type": "AzureKeyVaultSecret",
									"store": {
										"referenceName": "LS_AKV",
										"type": "LinkedServiceReference"
									},
									"secretName": "knimeappsecret"
								}
							}
						}
					}
				],
				"policy": {
					"elapsedTimeMetric": {}
				},
				"annotations": [],
				"lastPublishTime": "2026-04-16T06:51:50Z"
			},
			"dependsOn": [
				"[concat(variables('factoryId'), '/linkedServices/LS_AKV')]"
			]
		},
		{
			"name": "[concat(parameters('factoryName'), '/AzureDatabricks')]",
			"type": "Microsoft.DataFactory/factories/linkedServices",
			"apiVersion": "2018-06-01",
			"properties": {
				"annotations": [],
				"type": "AzureDatabricks",
				"typeProperties": {
					"domain": "https://adb-7405619109510762.2.azuredatabricks.net",
					"accessToken": {
						"type": "AzureKeyVaultSecret",
						"store": {
							"referenceName": "LS_AKV",
							"type": "LinkedServiceReference"
						},
						"secretName": "Databricks-Access-Token"
					},
					"existingClusterId": "[parameters('AzureDatabricks_properties_typeProperties_existingClusterId')]"
				}
			},
			"dependsOn": [
				"[concat(variables('factoryId'), '/linkedServices/LS_AKV')]"
			]
		},
		{
			"name": "[concat(parameters('factoryName'), '/LS_ADLS_Bronze')]",
			"type": "Microsoft.DataFactory/factories/linkedServices",
			"apiVersion": "2018-06-01",
			"properties": {
				"annotations": [],
				"type": "AzureBlobFS",
				"typeProperties": {
					"url": "[parameters('LS_ADLS_Bronze_properties_typeProperties_url')]",
					"credential": {
						"referenceName": "gh-datacycle-oidc",
						"type": "CredentialReference"
					}
				}
			},
			"dependsOn": [
				"[concat(variables('factoryId'), '/credentials/gh-datacycle-oidc')]"
			]
		},
		{
			"name": "[concat(parameters('factoryName'), '/LS_AzureFileShare_SAC')]",
			"type": "Microsoft.DataFactory/factories/linkedServices",
			"apiVersion": "2018-06-01",
			"properties": {
				"annotations": [],
				"type": "AzureFileStorage",
				"typeProperties": {
					"connectionString": "[parameters('LS_AzureFileShare_SAC_connectionString')]",
					"accountKey": {
						"type": "AzureKeyVaultSecret",
						"store": {
							"referenceName": "LS_AKV",
							"type": "LinkedServiceReference"
						},
						"secretName": "adls-access-key"
					},
					"fileShare": "sac-export-share"
				}
			},
			"dependsOn": [
				"[concat(variables('factoryId'), '/linkedServices/LS_AKV')]"
			]
		},
		{
			"name": "[concat(parameters('factoryName'), '/LS_BellevueBooking_LocalServer')]",
			"type": "Microsoft.DataFactory/factories/linkedServices",
			"apiVersion": "2018-06-01",
			"properties": {
				"annotations": [],
				"type": "FileServer",
				"typeProperties": {
					"host": "[parameters('LS_BellevueBooking_LocalServer_properties_typeProperties_host')]",
					"userId": "[parameters('LS_BellevueBooking_LocalServer_properties_typeProperties_userId')]",
					"password": {
						"type": "AzureKeyVaultSecret",
						"store": {
							"referenceName": "LS_AKV",
							"type": "LinkedServiceReference"
						},
						"secretName": "Student-VM-Password"
					}
				},
				"connectVia": {
					"referenceName": "Group3-VM-Runtime",
					"type": "IntegrationRuntimeReference"
				}
			},
			"dependsOn": [
				"[concat(variables('factoryId'), '/integrationRuntimes/Group3-VM-Runtime')]",
				"[concat(variables('factoryId'), '/linkedServices/LS_AKV')]"
			]
		},
		{
			"name": "[concat(parameters('factoryName'), '/LS_BellevueConso_LocalServer')]",
			"type": "Microsoft.DataFactory/factories/linkedServices",
			"apiVersion": "2018-06-01",
			"properties": {
				"annotations": [],
				"type": "FileServer",
				"typeProperties": {
					"host": "[parameters('LS_BellevueConso_LocalServer_properties_typeProperties_host')]",
					"userId": "[parameters('LS_BellevueConso_LocalServer_properties_typeProperties_userId')]",
					"password": {
						"type": "AzureKeyVaultSecret",
						"store": {
							"referenceName": "LS_AKV",
							"type": "LinkedServiceReference"
						},
						"secretName": "Student-VM-Password"
					}
				},
				"connectVia": {
					"referenceName": "Group3-VM-Runtime",
					"type": "IntegrationRuntimeReference"
				}
			},
			"dependsOn": [
				"[concat(variables('factoryId'), '/integrationRuntimes/Group3-VM-Runtime')]",
				"[concat(variables('factoryId'), '/linkedServices/LS_AKV')]"
			]
		},
		{
			"name": "[concat(parameters('factoryName'), '/LS_DevDB_Gold')]",
			"type": "Microsoft.DataFactory/factories/linkedServices",
			"apiVersion": "2018-06-01",
			"properties": {
				"annotations": [],
				"type": "AzureSqlDatabase",
				"typeProperties": {
					"server": "[parameters('LS_DevDB_Gold_properties_typeProperties_server')]",
					"database": "[parameters('LS_DevDB_Gold_properties_typeProperties_database')]",
					"encrypt": "mandatory",
					"trustServerCertificate": false,
					"authenticationType": "SQL",
					"userName": "[parameters('LS_DevDB_Gold_properties_typeProperties_userName')]",
					"password": {
						"type": "AzureKeyVaultSecret",
						"store": {
							"referenceName": "LS_AKV",
							"type": "LinkedServiceReference"
						},
						"secretName": "Admin-SQL-Password"
					}
				}
			},
			"dependsOn": [
				"[concat(variables('factoryId'), '/linkedServices/LS_AKV')]"
			]
		},
		{
			"name": "[concat(parameters('factoryName'), '/LS_SFTP_LocalServer')]",
			"type": "Microsoft.DataFactory/factories/linkedServices",
			"apiVersion": "2018-06-01",
			"properties": {
				"annotations": [],
				"type": "Sftp",
				"typeProperties": {
					"host": "[parameters('LS_SFTP_LocalServer_properties_typeProperties_host')]",
					"port": 22,
					"skipHostKeyValidation": true,
					"authenticationType": "Basic",
					"userName": "[parameters('LS_SFTP_LocalServer_properties_typeProperties_userName')]",
					"password": {
						"type": "AzureKeyVaultSecret",
						"store": {
							"referenceName": "LS_AKV",
							"type": "LinkedServiceReference"
						},
						"secretName": "Student-VM-Password"
					}
				},
				"connectVia": {
					"referenceName": "Group3-VM-Runtime",
					"type": "IntegrationRuntimeReference"
				}
			},
			"dependsOn": [
				"[concat(variables('factoryId'), '/integrationRuntimes/Group3-VM-Runtime')]",
				"[concat(variables('factoryId'), '/linkedServices/LS_AKV')]"
			]
		},
		{
			"name": "[concat(parameters('factoryName'), '/LS_Solarlogs_LocalServer')]",
			"type": "Microsoft.DataFactory/factories/linkedServices",
			"apiVersion": "2018-06-01",
			"properties": {
				"annotations": [],
				"type": "FileServer",
				"typeProperties": {
					"host": "[parameters('LS_Solarlogs_LocalServer_properties_typeProperties_host')]",
					"userId": "[parameters('LS_Solarlogs_LocalServer_properties_typeProperties_userId')]",
					"password": {
						"type": "AzureKeyVaultSecret",
						"store": {
							"referenceName": "LS_AKV",
							"type": "LinkedServiceReference"
						},
						"secretName": "Student-VM-Password"
					}
				},
				"connectVia": {
					"referenceName": "Group3-VM-Runtime",
					"type": "IntegrationRuntimeReference"
				}
			},
			"dependsOn": [
				"[concat(variables('factoryId'), '/integrationRuntimes/Group3-VM-Runtime')]",
				"[concat(variables('factoryId'), '/linkedServices/LS_AKV')]"
			]
		},
		{
			"name": "[concat(parameters('factoryName'), '/PL_Upload_Pred_Gold')]",
			"type": "Microsoft.DataFactory/factories/pipelines",
			"apiVersion": "2018-06-01",
			"properties": {
				"activities": [
					{
						"name": "Load Predictions to Gold",
						"type": "DatabricksNotebook",
						"dependsOn": [
							{
								"activity": "Knime Run",
								"dependencyConditions": [
									"Succeeded"
								]
							}
						],
						"policy": {
							"timeout": "0.12:00:00",
							"retry": 0,
							"retryIntervalInSeconds": 30,
							"secureOutput": false,
							"secureInput": false
						},
						"userProperties": [],
						"typeProperties": {
							"notebookPath": "/Users/dylan.sanderso@hes-so.ch/ADF_DataCycleProject/databricks/notebooks/ml_load_predictions"
						},
						"linkedServiceName": {
							"referenceName": "AzureDatabricks",
							"type": "LinkedServiceReference"
						}
					},
					{
						"name": "Knime Run",
						"type": "ExecutePipeline",
						"dependsOn": [],
						"policy": {
							"secureInput": false
						},
						"userProperties": [],
						"typeProperties": {
							"pipeline": {
								"referenceName": "Run_Knime",
								"type": "PipelineReference"
							},
							"waitOnCompletion": true,
							"parameters": {}
						}
					}
				],
				"policy": {
					"elapsedTimeMetric": {}
				},
				"annotations": [],
				"lastPublishTime": "2026-04-16T06:51:50Z"
			},
			"dependsOn": [
				"[concat(variables('factoryId'), '/linkedServices/AzureDatabricks')]",
				"[concat(variables('factoryId'), '/pipelines/Run_Knime')]"
			]
		},
		{
			"name": "[concat(parameters('factoryName'), '/DS_ADLS_SACStaging')]",
			"type": "Microsoft.DataFactory/factories/datasets",
			"apiVersion": "2018-06-01",
			"properties": {
				"linkedServiceName": {
					"referenceName": "LS_ADLS_Bronze",
					"type": "LinkedServiceReference"
				},
				"annotations": [],
				"type": "Binary",
				"typeProperties": {
					"location": {
						"type": "AzureBlobFSLocation",
						"fileSystem": "sacexport"
					}
				}
			},
			"dependsOn": [
				"[concat(variables('factoryId'), '/linkedServices/LS_ADLS_Bronze')]"
			]
		},
		{
			"name": "[concat(parameters('factoryName'), '/DS_FileShare_SAC')]",
			"type": "Microsoft.DataFactory/factories/datasets",
			"apiVersion": "2018-06-01",
			"properties": {
				"linkedServiceName": {
					"referenceName": "LS_AzureFileShare_SAC",
					"type": "LinkedServiceReference"
				},
				"annotations": [],
				"type": "Binary",
				"typeProperties": {
					"location": {
						"type": "AzureFileStorageLocation"
					}
				}
			},
			"dependsOn": [
				"[concat(variables('factoryId'), '/linkedServices/LS_AzureFileShare_SAC')]"
			]
		},
		{
			"name": "[concat(parameters('factoryName'), '/DS_Vetroz_Booking_Bronze')]",
			"type": "Microsoft.DataFactory/factories/datasets",
			"apiVersion": "2018-06-01",
			"properties": {
				"linkedServiceName": {
					"referenceName": "LS_ADLS_Bronze",
					"type": "LinkedServiceReference"
				},
				"annotations": [],
				"type": "Binary",
				"typeProperties": {
					"location": {
						"type": "AzureBlobFSLocation",
						"folderPath": "bookings",
						"fileSystem": "bronze"
					}
				}
			},
			"dependsOn": [
				"[concat(variables('factoryId'), '/linkedServices/LS_ADLS_Bronze')]"
			]
		},
		{
			"name": "[concat(parameters('factoryName'), '/DS_Vetroz_Booking_Source')]",
			"type": "Microsoft.DataFactory/factories/datasets",
			"apiVersion": "2018-06-01",
			"properties": {
				"linkedServiceName": {
					"referenceName": "LS_BellevueBooking_LocalServer",
					"type": "LinkedServiceReference"
				},
				"annotations": [],
				"type": "Binary",
				"typeProperties": {
					"location": {
						"type": "FileServerLocation"
					}
				}
			},
			"dependsOn": [
				"[concat(variables('factoryId'), '/linkedServices/LS_BellevueBooking_LocalServer')]"
			]
		},
		{
			"name": "[concat(parameters('factoryName'), '/DS_Vetroz_Conso_Bronze')]",
			"type": "Microsoft.DataFactory/factories/datasets",
			"apiVersion": "2018-06-01",
			"properties": {
				"linkedServiceName": {
					"referenceName": "LS_ADLS_Bronze",
					"type": "LinkedServiceReference"
				},
				"parameters": {
					"p_folder": {
						"type": "string",
						"defaultValue": "others"
					}
				},
				"annotations": [],
				"type": "Binary",
				"typeProperties": {
					"location": {
						"type": "AzureBlobFSLocation",
						"folderPath": {
							"value": "@dataset().p_folder",
							"type": "Expression"
						},
						"fileSystem": "bronze"
					}
				}
			},
			"dependsOn": [
				"[concat(variables('factoryId'), '/linkedServices/LS_ADLS_Bronze')]"
			]
		},
		{
			"name": "[concat(parameters('factoryName'), '/DS_Vetroz_Conso_Source')]",
			"type": "Microsoft.DataFactory/factories/datasets",
			"apiVersion": "2018-06-01",
			"properties": {
				"linkedServiceName": {
					"referenceName": "LS_BellevueConso_LocalServer",
					"type": "LinkedServiceReference"
				},
				"annotations": [],
				"type": "Binary",
				"typeProperties": {
					"location": {
						"type": "FileServerLocation"
					}
				}
			},
			"dependsOn": [
				"[concat(variables('factoryId'), '/linkedServices/LS_BellevueConso_LocalServer')]"
			]
		}
	]
}